unicodeconverter/__init__.py
unicodeconverter/converter.py
unicodeconverter/version.txt
unicodeconverter/lists/__init__.py
unicodeconverter/maps/__init__.py
unicodeconverter/utils/__init__.py
unicodeconverter/utils/checkers.py
unicodeconverter/utils/rearrange.py
unicodeconverter-0.1.0b12.dist-info/LICENSE
unicodeconverter-0.1.0b12.dist-info/METADATA
unicodeconverter-0.1.0b12.dist-info/WHEEL
unicodeconverter-0.1.0b12.dist-info/top_level.txt
unicodeconverter-0.1.0b12.dist-info/RECORD
